aivk_web/__init__.py
aivk_web/py.typed
aivk_web/backend/Dockerfile
aivk_web/backend/aivkw.py
aivk_web/backend/requirements.txt
aivk_web/frontend/.gitignore
aivk_web/frontend/README.md
aivk_web/frontend/index.html
aivk_web/frontend/package-lock.json
aivk_web/frontend/package.json
aivk_web/frontend/tsconfig.app.json
aivk_web/frontend/tsconfig.json
aivk_web/frontend/tsconfig.node.json
aivk_web/frontend/vite.config.ts
aivk_web/frontend/.vscode/extensions.json
aivk_web/frontend/dist/index.html
aivk_web/frontend/dist/vite.svg
aivk_web/frontend/dist/assets/index-CwTTb9ZP.js
aivk_web/frontend/dist/assets/index-DYO2j8qy.css
aivk_web/frontend/node_modules/.package-lock.json
aivk_web/frontend/node_modules/.bin/esbuild
aivk_web/frontend/node_modules/.bin/esbuild.cmd
aivk_web/frontend/node_modules/.bin/esbuild.ps1
aivk_web/frontend/node_modules/.bin/he
aivk_web/frontend/node_modules/.bin/he.cmd
aivk_web/frontend/node_modules/.bin/he.ps1
aivk_web/frontend/node_modules/.bin/nanoid
aivk_web/frontend/node_modules/.bin/nanoid.cmd
aivk_web/frontend/node_modules/.bin/nanoid.ps1
aivk_web/frontend/node_modules/.bin/parser
aivk_web/frontend/node_modules/.bin/parser.cmd
aivk_web/frontend/node_modules/.bin/parser.ps1
aivk_web/frontend/node_modules/.bin/rollup
aivk_web/frontend/node_modules/.bin/rollup.cmd
aivk_web/frontend/node_modules/.bin/rollup.ps1
aivk_web/frontend/node_modules/.bin/tsc
aivk_web/frontend/node_modules/.bin/tsc.cmd
aivk_web/frontend/node_modules/.bin/tsc.ps1
aivk_web/frontend/node_modules/.bin/tsserver
aivk_web/frontend/node_modules/.bin/tsserver.cmd
aivk_web/frontend/node_modules/.bin/tsserver.ps1
aivk_web/frontend/node_modules/.bin/vite
aivk_web/frontend/node_modules/.bin/vite.cmd
aivk_web/frontend/node_modules/.bin/vite.ps1
aivk_web/frontend/node_modules/.bin/vue-tsc
aivk_web/frontend/node_modules/.bin/vue-tsc.cmd
aivk_web/frontend/node_modules/.bin/vue-tsc.ps1
aivk_web/frontend/node_modules/.tmp/tsconfig.app.tsbuildinfo
aivk_web-0.1.2.dist-info/METADATA
aivk_web-0.1.2.dist-info/WHEEL
aivk_web-0.1.2.dist-info/RECORD
